COPYING
MANIFEST.in
README.md
setup.cfg
setup.py
ansible_roles/__init__.py
ansible_roles/__init__.pyc
ansible_roles.egg-info/PKG-INFO
ansible_roles.egg-info/SOURCES.txt
ansible_roles.egg-info/dependency_links.txt
ansible_roles.egg-info/top_level.txt
bin/ansible-roles