Metadata-Version: 1.1
Name: ansible-roles
Version: 0.1.4
Summary: Manage ansible roles.
Home-page: https://pikacode.com/meister/ansible-roles
Author: Benjamin Jorand
Author-email: benjamin.jorand@gmail.com
License: MIT
Keywords: ansible roles
Platform: UNKNOWN
Classifier: Environment :: Console
Classifier: Operating System :: OS Independent
Classifier: Programming Language :: Python :: 2
Classifier: Programming Language :: Python :: 2.5
Classifier: Programming Language :: Python :: 2.6
Classifier: Programming Language :: Python :: 2.7
Classifier: Programming Language :: Python :: 3
Classifier: Programming Language :: Python :: 3.1
Classifier: Programming Language :: Python :: 3.2
Classifier: Programming Language :: Python :: 3.3
Classifier: Programming Language :: Python :: 3.4
Classifier: Development Status :: 5 - Production/Stable
Classifier: Topic :: Utilities
Classifier: License :: OSI Approved :: MIT License
